{
  "fluentMethods": true,
  "clientRootFolder": "",
  "relationships": [
    {
      "relationshipName": "offer",
      "otherEntityName": "offer",
      "relationshipType": "one-to-many",
      "otherEntityRelationshipName": "latLng"
    }
  ],
  "fields": [
    {
      "fieldName": "latitude",
      "fieldType": "Double"
    },
    {
      "fieldName": "longitude",
      "fieldType": "Double"
    }
  ],
  "changelogDate": "20210218235238",
  "dto": "no",
  "searchEngine": false,
  "service": "serviceImpl",
  "entityTableName": "lat_lng",
  "databaseType": "sql",
  "readOnly": false,
  "jpaMetamodelFiltering": false,
  "pagination": "no"
}
